README.md
setup.py
Talent_Model_UnitTest/step_page/__init__.py
Talent_Model_UnitTest/step_page/case_data.py
Talent_Model_UnitTest/step_page/test_demo.py
b_c_components/__init__.py
b_c_components/get_environment.py
b_c_components/get_memory_data.py
b_c_components/pytest_model.py
b_c_components/Intercept_requests/__init__.py
b_c_components/Intercept_requests/selenium_network.py
b_c_components/custom_module/__init__.py
b_c_components/custom_module/custom_exception.py
b_c_components/driver/__init__.py
b_c_components/driver/linux/__init__.py
b_c_components/driver/linux/chrome/__init__.py
b_c_components/driver/mac/__init__.py
b_c_components/driver/mac/chrome/__init__.py
b_c_components/driver/win/__init__.py
b_c_components/driver/win/chrome/__init__.py
b_c_components/get_b_version/__init__.py
b_c_components/get_b_version/get_version.py
b_c_components/get_config/__init__.py
b_c_components/get_config/get_config.py
b_c_components/get_config/get_project_root_path.py
b_c_components/get_excel/__init__.py
b_c_components/get_excel/do_excel.py
b_c_components/log/__init__.py
b_c_components/log/log.py
bs_ui_auto_c_c.egg-info/PKG-INFO
bs_ui_auto_c_c.egg-info/SOURCES.txt
bs_ui_auto_c_c.egg-info/dependency_links.txt
bs_ui_auto_c_c.egg-info/requires.txt
bs_ui_auto_c_c.egg-info/top_level.txt
v3_components/__init__.py
v3_components/page/__init__.py
v3_components/page/login.py
v5_components/__init__.py
v5_components/page/__init__.py
v5_components/page/modlues.py