Metadata-Version: 2.1
Name: bs-ui-auto-c-c
Version: 0.0.52
Summary: 一个selenium自动安装驱动、日志的项目
Home-page: UNKNOWN
Author: sijunji
Author-email: sijunji@outlook.com
License: apache3.0
Platform: UNKNOWN
